{
  "pipeline_status": "COMPLETE",
  "video_processed": "test_video.mp4",
  "total_segments": 25,
  "audio_segments": 14,
  "visual_segments": 11,
  "files_generated": [
    "data\\transcripts\\test_video.json",
    "data\\transcripts\\test_video_semantic.json",
    "data\\embeddings\\test_video_embeddings.json",
    "data\\embeddings\\test_video_frame_embeddings.json"
  ],
  "chromadb_ready": true,
  "next_steps": [
    "Install compatible ChromaDB version",
    "Ingest data using Phase 3 components",
    "Test multimodal search queries",
    "Implement Phase 4-6 for complete RAG system"
  ]
}